<?xml version="1.0" encoding="utf-8" ?>
<!-- Copyright 2022 OpenSynergy Indonesia
     Copyright 2022 PT. Simetri Sinergi Indonesia
     License AGPL-3.0 or later (http://www.gnu.org/licenses/agpl). -->
<odoo>

<record id="demo_overtime_type1" model="hr.overtime_type">
    <field name="name">Daily Overtime - (test)</field>
    <field name="code">OT01</field>
    <field name="apply_limit_per_day">True</field>
    <field name="limit_per_day">6</field>
</record>

<record id="demo_overtime_type2" model="hr.overtime_type">
    <field name="name">Holiday Overtime - (test)</field>
    <field name="code">OT02</field>
    <field name="apply_limit_per_day">False</field>
</record>

</odoo>
